azure/communication/identity/__init__.py
azure/communication/identity/_api_versions.py
azure/communication/identity/_communication_identity_client.py
azure/communication/identity/_utils.py
azure/communication/identity/_version.py
azure/communication/identity/py.typed
azure/communication/identity/_generated/__init__.py
azure/communication/identity/_generated/_client.py
azure/communication/identity/_generated/_configuration.py
azure/communication/identity/_generated/_patch.py
azure/communication/identity/_generated/_serialization.py
azure/communication/identity/_generated/py.typed
azure/communication/identity/_generated/aio/__init__.py
azure/communication/identity/_generated/aio/_client.py
azure/communication/identity/_generated/aio/_configuration.py
azure/communication/identity/_generated/aio/_patch.py
azure/communication/identity/_generated/aio/operations/__init__.py
azure/communication/identity/_generated/aio/operations/_operations.py
azure/communication/identity/_generated/aio/operations/_patch.py
azure/communication/identity/_generated/models/__init__.py
azure/communication/identity/_generated/models/_enums.py
azure/communication/identity/_generated/models/_models.py
azure/communication/identity/_generated/models/_patch.py
azure/communication/identity/_generated/operations/__init__.py
azure/communication/identity/_generated/operations/_operations.py
azure/communication/identity/_generated/operations/_patch.py
azure/communication/identity/_shared/__init__.py
azure/communication/identity/_shared/auth_policy_utils.py
azure/communication/identity/_shared/models.py
azure/communication/identity/_shared/policy.py
azure/communication/identity/_shared/user_credential.py
azure/communication/identity/_shared/user_credential_async.py
azure/communication/identity/_shared/utils.py
azure/communication/identity/_shared/utils_async.py
azure/communication/identity/aio/__init__.py
azure/communication/identity/aio/_communication_identity_client_async.py
azure_communication_identity-1.4.0.dist-info/LICENSE
azure_communication_identity-1.4.0.dist-info/METADATA
azure_communication_identity-1.4.0.dist-info/WHEEL
azure_communication_identity-1.4.0.dist-info/top_level.txt
azure_communication_identity-1.4.0.dist-info/RECORD
